axmp_openapi_mcp_server/__init__.py
axmp_openapi_mcp_server/__main__.py
axmp_openapi_mcp_server/openapi_mcp_server.py
axmp_openapi_mcp_server/setting.py
axmp_openapi_mcp_server/runner/cli.py
axmp_openapi_mcp_server/runner/container.py
axmp_openapi_mcp_server-0.2.2.dist-info/METADATA
axmp_openapi_mcp_server-0.2.2.dist-info/WHEEL
axmp_openapi_mcp_server-0.2.2.dist-info/entry_points.txt
axmp_openapi_mcp_server-0.2.2.dist-info/licenses/LICENSE
axmp_openapi_mcp_server-0.2.2.dist-info/RECORD
