Metadata-Version: 2.4
Name: axmp-openapi-mcp-server
Version: 0.2.2
Summary: This is a template mcp server for the axmp-ai-agent-studio
Project-URL: homepage, https://github.com/cloudz-mp
Project-URL: repository, https://github.com/cloudz-mp/axmp-openapi-mcp-server
Project-URL: documentation, https://github.com/cloudz-mp/axmp-openapi-mcp-server
Project-URL: Bug Tracker, https://github.com/cloudz-mp/axmp-openapi-mcp-server/issues
Author-email: Kilsoo Kang <kilsoo75@gmail.com>
License-File: LICENSE
Requires-Python: <4.0,>=3.12
Requires-Dist: axmp-openapi-helper>=0.2.0
Requires-Dist: click>=8.2.1
Requires-Dist: mcp>=1.10.1
Requires-Dist: pydantic>=2.11.7
Requires-Dist: python-dotenv>=1.1.1
